<?xml version="1.0" encoding="UTF-8"?>
<ProActiveDescriptor xmlns:xsi="http://www.w3.org/2001/XMLSchema-instance" xsi:noNamespaceSchemaLocation="DescriptorSchema.xsd">
	<componentDefinition>
		<virtualNodesDefinition>
			<virtualNode name="p2pvn" property="multiple"  />
		</virtualNodesDefinition>
	</componentDefinition>
	<deployment>
		<mapping>
			<map virtualNode="p2pvn">
				<jvmSet>
					<vmName value="Jvm1"/>
				</jvmSet>
			</map>
		</mapping>
		<jvms>
			<jvm name="Jvm1">
				<acquisition>
					<serviceReference refid="p2pservice"/>
				</acquisition>
			</jvm>
		</jvms>
	</deployment>
	<infrastructure>
	<processes>
		<services>
			<serviceDefinition id="p2pservice">
				<P2PService nodesAsked="2" port="6667" NOA="10" TTU="60000" TTL="10">
					<peerSet>
						<peer>rmi://tranquility.inria.fr:6666</peer>
					</peerSet>
				</P2PService>
			</serviceDefinition>
		</services>
	 </processes>
	</infrastructure>
</ProActiveDescriptor>
